pgconnstr.py
pgconnstr-1.0.1.dist-info/LICENSE
pgconnstr-1.0.1.dist-info/METADATA
pgconnstr-1.0.1.dist-info/WHEEL
pgconnstr-1.0.1.dist-info/top_level.txt
pgconnstr-1.0.1.dist-info/RECORD
