Metadata-Version: 2.1
Name: pgconnstr
Version: 1.0.1
Summary: A tool for parsing and manipulating PostgreSQL libpq style connection strings and URIs
Home-page: https://github.com/canonical/pgconnstr
Author: Stuart Bishop
Author-email: stuart.bishop@canonical.com
Maintainer: PostgreSQL Charmers
Maintainer-email: postgresql-charmers@lists.canonical.com
License: UNKNOWN
Keywords: PostgreSQL,postgres
Platform: UNKNOWN
Classifier: Development Status :: 5 - Production/Stable
Classifier: Programming Language :: Python :: 3 :: Only
Classifier: Programming Language :: Python :: 3.6
Classifier: Programming Language :: Python :: 3.7
Classifier: Programming Language :: Python :: 3.8
Classifier: Programming Language :: Python :: 3.9
Classifier: License :: OSI Approved :: GNU Lesser General Public License v3 (LGPLv3)
Classifier: Operating System :: OS Independent
Requires-Python: >=3.6
